[{"idOfCrawler": 1, "type": "object", "properties": {"price": {"type": "number"}, "count": {"type": "number"}, "name": {"type": "string"}, "customer name": {"type": "string"}, "phone number": {"type": "string"}}}, {"type": "object", "properties": {"legs": {"type": "number"}}, "idOfCrawler": 2}, {"type": "object", "properties": {"name": {"type": "string"}, "count": {"type": "integer"}, "price": {"type": "number"}, "customer name": {"type": "string"}}, "idOfCrawler": 3}, {"type": "object", "properties": {"name": {"type": "string"}, "count": {"type": "integer"}, "price": {"type": "number"}, "customer name": {"type": "string"}, "date": {"type": "string", "format": "date-time"}, "list": {"type": "array"}}, "idOfCrawler": 4}, {"type": "object", "properties": {"name": {"type": "string"}, "count": {"type": "integer"}, "price": {"type": "number"}, "customer name": {"type": "string"}, "phone number": {"type": "string"}, "list": {"type": "array", "items": {"type": "string"}}}, "idOfCrawler": 5}, {"type": "object", "properties": {"name": {"type": "string"}, "count": {"type": "integer"}, "price": {"type": "number"}, "customer name": {"type": "string"}, "phone number": {"type": "string"}, "time": {"type": "string", "format": "date"}, "list": {"type": "array", "items": {"type": "string"}}}, "idOfCrawler": 6}, {"type": "object", "properties": {"name": {"type": "string"}, "count": {"type": "integer"}, "price": {"type": "number"}, "customer name": {"type": "string"}, "phone number": {"type": "string"}, "date": {"type": "string", "format": "date-time"}, "list": {"type": "array", "items": {"type": "string"}}}, "idOfCrawler": 7}, {"type": "object", "properties": {"name": {"type": "string"}, "count": {"type": "integer"}, "price": {"type": "number"}, "customer name": {"type": "string"}, "phone number": {"type": "string"}, "list": {"type": "array", "items": {"type": "string"}}}, "idOfCrawler": 8}, {"type": "object", "properties": {"name": {"type": "string"}, "count": {"type": "integer"}, "price": {"type": "number"}, "customer name": {"type": "string"}, "phone number": {"type": "string"}, "list": {"type": "array", "items": {"type": "string"}}, "date": {"type": "string", "format": "date"}}, "idOfCrawler": 9}, {"type": "object", "properties": {"title": {"type": "string"}, "date": {"type": "string"}, "text": {"type": "string"}, "tags": {"type": "array", "items": {"type": "string"}}, "links": {"type": "array"}}, "idOfCrawler": 10}, {"type": "object", "properties": {"title": {"type": "string"}, "date": {"type": "string", "format": "date-time"}, "text": {"type": "string"}, "tags": {"type": "array", "items": {"type": "string"}}, "links": {"type": "array"}}, "idOfCrawler": 11}, {"type": "object", "properties": {"type": {"type": "string"}, "url": {"type": "string"}, "title": {"type": "string"}, "image": {"type": "string"}, "text": {"type": "string"}, "datetime": {"type": "string", "format": "timestamp"}, "tags": {"type": "array", "items": {"type": "string"}}, "agency": {"type": "string"}, "platform": {"type": "string"}, "datetime_modified": {"type": "string", "format": "timestamp"}}, "idOfCrawler": 12}, {"type": "object", "properties": {"type": {"type": "string"}, "url": {"type": "string"}, "title": {"type": "string"}, "story_url": {"type": "string"}, "text": {"type": "string"}, "datetime": {"type": "string", "format": "timestamp"}, "agency": {"type": "string"}, "platform": {"type": "string"}, "category": {"type": "string"}}, "idOfCrawler": 13}]