[{"idOfCrawler": 7, "name": "ytexg", "count": 14, "price": 2.586, "customer name": "mwx", "phone number": "+79324554811", "date": "2014-11-20T15:09:31", "list": ["hbbrz", "iqynk", "smtx", "anpggl", "pjlhckqzl", "medz", "gioworz"]}, {"idOfCrawler": 7, "name": "fgxsrmdmj", "count": 4, "price": 7.232, "customer name": "ibbadbnpl", "phone number": "+79589639236", "date": "2014-11-20T14:21:45", "list": ["wmtulxwfp", "yqavk", "sidcutgquv", "nsf"]}, {"idOfCrawler": 7, "name": "sumdbiyj", "count": 2, "price": 7.257, "customer name": "vmcee", "phone number": "+79990280673", "date": "2014-11-20T04:41:49", "list": ["fdgrxavzd", "plhnhgk", "bqdg", "cyr", "casowzzqqw", "qonkglpvl", "advvtcqk"]}, {"idOfCrawler": 7, "name": "kxyolpnvoa", "count": 11, "price": 10.479, "customer name": "ryrxn", "phone number": "+79693477484", "date": "2014-11-20T18:56:33", "list": ["oxjhguvpiq", "cyljbfu", "vzgwogryb", "ulwhern"]}, {"idOfCrawler": 7, "name": "fvusaqjh", "count": 6, "price": 11.715, "customer name": "eesrpt", "phone number": "+79551002225", "date": "2014-11-21T09:10:49", "list": ["zbpjrl", "tjprb", "tox", "cnzugzl"]}, {"idOfCrawler": 7, "name": "cffdwxghb", "count": 12, "price": 8.924, "customer name": "wvfokrh", "phone number": "+79775020404", "date": "2014-11-20T20:02:21", "list": ["peycaichp", "nrmlx", "xkcgjzndrm", "acziqhdgau"]}, {"idOfCrawler": 7, "name": "eakmghejg", "count": 7, "price": 6.122, "customer name": "vtsfumsxj", "phone number": "+79438310743", "date": "2014-11-21T14:49:07", "list": ["eerelawnim", "egcfj", "axqdpojax", "umfvzx"]}, {"idOfCrawler": 7, "name": "bck", "count": 14, "price": 14.850999999999999, "customer name": "yeajixecs", "phone number": "+79777076503", "date": "2014-11-21T05:03:11", "list": ["fcj", "xoi", "pwrcmqduzk", "fnha", "iqscrveqjy", "scera", "xdbbd"]}, {"idOfCrawler": 7, "name": "gxg", "count": 3, "price": 15.218, "customer name": "pkuhfqelj", "phone number": "+79720057289", "date": "2014-11-21T12:26:29", "list": ["tgeuzr", "hzwsqnu", "qvav", "bintkmwllk", "nrb"]}, {"idOfCrawler": 7, "name": "gplytutt", "count": 4, "price": 3.255, "customer name": "xatnm", "phone number": "+79632881428", "date": "2014-11-20T14:12:28", "list": ["jnwqdiqzg", "miyr", "rudhpgzbnn", "dxvanf", "eszkewuc", "wzxhaetet", "rchltnq", "tifmw"]}, {"idOfCrawler": 7, "name": "xzikgklx", "count": 14, "price": 18.416, "customer name": "niyctxl", "phone number": "+79949064200", "date": "2014-11-20T16:22:03", "list": ["nbsdckxnq", "dqt", "zbtajm", "tghi", "mfly", "xowmdoo", "tcpbor", "vunueeuc"]}, {"idOfCrawler": 7, "name": "yoeqx", "count": 1, "price": 8.276, "customer name": "twwuc", "phone number": "+79467865943", "date": "2014-11-20T06:50:52", "list": ["uvahbew", "mzxhrc", "runx", "fdjor", "gdt"]}, {"idOfCrawler": 7, "name": "kcq", "count": 3, "price": 18.007, "customer name": "naxrvwxz", "phone number": "+79402983951", "date": "2014-11-20T09:55:21", "list": ["jxhazjcfn", "dzcnfzppr", "mwuwpmxw", "oiakc", "vvqpekmgpv", "jhnzshsw", "pyti", "ahss"]}, {"idOfCrawler": 7, "name": "wady", "count": 5, "price": 17.847, "customer name": "jjpkjld", "phone number": "+79120996729", "date": "2014-11-21T00:28:35", "list": ["hvxfxk", "jbu", "getrnhn", "xvn", "ycfpgds", "xop", "bkasfzxc", "xktou"]}, {"idOfCrawler": 7, "name": "odwintvdds", "count": 4, "price": 14.471, "customer name": "onso", "phone number": "+79771024703", "date": "2014-11-21T13:11:02", "list": ["pygnou", "ztocypwsat", "qsnxfxnpp", "rgjaszw", "cckgr", "ncxxmxayo", "ygukdjj"]}, {"idOfCrawler": 7, "name": "vnb", "count": 7, "price": 8.039, "customer name": "juuqgja", "phone number": "+79952515883", "date": "2014-11-22T12:22:21", "list": ["djxdevq", "icbbitmpq", "buvnlblgc", "llmgu", "azshzvu", "whgrasv"]}, {"idOfCrawler": 7, "name": "nwdlq", "count": 7, "price": 4.2, "customer name": "vuxjf", "phone number": "+79650219539", "date": "2014-11-23T11:58:46", "list": ["svc", "lrg", "tynahldct", "ybileku", "abwvyz", "jzedy", "rvidx"]}, {"idOfCrawler": 7, "name": "zrfrrogy", "count": 11, "price": 4.18, "customer name": "lspeiaq", "phone number": "+79776974503", "date": "2014-11-23T11:50:48", "list": ["vcqxste", "rtbpichfzk", "vfqiskfnr", "vmuceqi", "cngxwod"]}, {"idOfCrawler": 7, "name": "jdyg", "count": 7, "price": 7.214, "customer name": "mhtuof", "phone number": "+79494776786", "date": "2014-11-23T16:36:56", "list": ["lrtfxkw", "qbzstg", "ncn", "hqwgyfp", "ksblxqxt"]}, {"idOfCrawler": 7, "name": "lvonujf", "count": 14, "price": 11.054, "customer name": "niidbm", "phone number": "+79970726252", "date": "2014-11-24T10:53:39", "list": ["vefyfd", "mtocdcsw", "umcvuzrjzq", "wsekbsrin", "lhacovwd", "qdvqqqsfe"]}]